redis_sentinel_url.py
Redis_Sentinel_Url-1.0.1.dist-info/DESCRIPTION.rst
Redis_Sentinel_Url-1.0.1.dist-info/METADATA
Redis_Sentinel_Url-1.0.1.dist-info/RECORD
Redis_Sentinel_Url-1.0.1.dist-info/WHEEL
Redis_Sentinel_Url-1.0.1.dist-info/metadata.json
Redis_Sentinel_Url-1.0.1.dist-info/pbr.json
Redis_Sentinel_Url-1.0.1.dist-info/top_level.txt
